Metadata-Version: 2.1
Name: dvcdownload
Version: 0.2b1
Summary: A sample dvc project
Home-page: https://github.com/aman5319/DVC-DOWNLOAD
Author: Aman Pandey
Author-email: amanpandey5319@gmail.com
License: UNKNOWN
Project-URL: Bug Trackers, https://github.com/aman5319/DVC-DOWNLOAD/issues
Project-URL: Source, https://github.com/aman5319/DVC-DOWNLOAD
Project-URL: Documentation, https://github.com/aman5319/DVC-DOWNLOAD/blob/master/README.md
Keywords: dvc
Platform: UNKNOWN
Classifier: Development Status :: 4 - Beta
Classifier: Intended Audience :: Developers
Classifier: Intended Audience :: System Administrators
Classifier: License :: OSI Approved :: GNU General Public License v3 or later (GPLv3+)
Classifier: Programming Language :: Python :: 3 :: Only
Classifier: Programming Language :: Python :: 3.5
Classifier: Programming Language :: Python :: 3.6
Classifier: Programming Language :: Python :: 3.7
Classifier: Programming Language :: Python :: 3.8
Requires-Python: ~=3.5
